ailabeler/__init__.py
ailabeler/_version.py
ailabeler/app_info.py
ailabeler/config.py
ailabeler/main.py
ailabeler/utils.py
ailabeler/configs/__init__.py
ailabeler/configs/ailabeler_config.yaml
ailabeler/configs/auto_labeling/models.yaml
ailabeler/configs/auto_labeling/sam2_hiera_large_video.yaml
ailabeler/resources/__init__.py
ailabeler/resources/resources.py
ailabeler/resources/resources.qrc
ailabeler/resources/icons/arrow-left.svg
ailabeler/resources/icons/arrow-right.svg
ailabeler/resources/icons/caret-down.svg
ailabeler/resources/icons/caret-up.svg
ailabeler/resources/icons/check.svg
ailabeler/resources/icons/checkmark.svg
ailabeler/resources/icons/chevron-down.svg
ailabeler/resources/icons/clear.svg
ailabeler/resources/icons/click.svg
ailabeler/resources/icons/copy-green.svg
ailabeler/resources/icons/copy.svg
ailabeler/resources/icons/edit.svg
ailabeler/resources/icons/eraser.svg
ailabeler/resources/icons/error.svg
ailabeler/resources/icons/eye-off.svg
ailabeler/resources/icons/eye.svg
ailabeler/resources/icons/folder.svg
ailabeler/resources/icons/help-circle.svg
ailabeler/resources/icons/image.svg
ailabeler/resources/icons/import-export.svg
ailabeler/resources/icons/lightning.svg
ailabeler/resources/icons/refresh.svg
ailabeler/resources/icons/run.svg
ailabeler/resources/icons/search.svg
ailabeler/resources/icons/send.svg
ailabeler/resources/icons/star-black.svg
ailabeler/resources/icons/star.svg
ailabeler/resources/icons/starred.svg
ailabeler/resources/icons/stop.svg
ailabeler/resources/icons/trash.svg
ailabeler/resources/icons/video.svg
ailabeler/resources/icons/vision.svg
ailabeler/resources/icons/warning.svg
ailabeler/resources/images/auto-run.png
ailabeler/resources/images/brain.png
ailabeler/resources/images/cancel.png
ailabeler/resources/images/cartesian.png
ailabeler/resources/images/circle.png
ailabeler/resources/images/cn.png
ailabeler/resources/images/color.png
ailabeler/resources/images/contact.png
ailabeler/resources/images/convert.png
ailabeler-0.5.0.dist-info/licenses/LICENSE-GPLv3.txt
ailabeler-0.5.0.dist-info/licenses/LICENSE-apache.txt
ailabeler-0.5.0.dist-info/METADATA
ailabeler-0.5.0.dist-info/WHEEL
ailabeler-0.5.0.dist-info/entry_points.txt
ailabeler-0.5.0.dist-info/top_level.txt
ailabeler-0.5.0.dist-info/RECORD
